bitmake/__init__.py
bitmake/rest.py
bitmake/ws.py
tests/__init__.py
tests/test_apiclient.py
tests/test_restapi.py
tests/test_wsapi.py
bitmake-1.0.1.dist-info/METADATA
bitmake-1.0.1.dist-info/WHEEL
bitmake-1.0.1.dist-info/top_level.txt
bitmake-1.0.1.dist-info/RECORD
